featurelayers/__init__.py
featurelayers/__version__.py
featurelayers/example.py
featurelayers/layers/LBC.py
featurelayers/layers/LDP.py
featurelayers/layers/__init__.py
featurelayers/models/LBC_xception.py
featurelayers/models/__init__.py
featurelayers/models/xception.py
featurelayers-1.5.6.dist-info/METADATA
featurelayers-1.5.6.dist-info/WHEEL
featurelayers-1.5.6.dist-info/top_level.txt
featurelayers-1.5.6.dist-info/RECORD
