Metadata-Version: 2.1
Name: featurelayers
Version: 1.5.6
Summary: FeatureLayers Package
Author: khengyun
Author-email: khaangnguyeen@email.com
Classifier: Development Status :: 3 - Alpha
Classifier: Intended Audience :: Education
Classifier: Programming Language :: Python :: 3
Classifier: Operating System :: MacOS :: MacOS X
Classifier: Operating System :: Microsoft :: Windows
Requires-Dist: numpy
Requires-Dist: scipy
Requires-Dist: tensorflow
Requires-Dist: keras
Requires-Dist: rich
Requires-Dist: matplotlib
Requires-Dist: scikit-learn
Requires-Dist: graphviz
Requires-Dist: pydot
Requires-Dist: keras-applications
